Workbook

Sheet README & Assumptions
A1: Peanut eSIM — P&L Model v2
A2: Built 2026-05-31. Pay-per-order assumption: COGS = actual GB consumed (not pool size). All yellow cells = editable inputs.
A4: COLOR KEY
A5: Blue | B5: Hardcoded input — change at will
A6: Black | B6: Formula — do not edit
A7: Green | B7: Cross-sheet reference
A8: Yellow cell | B8: Key assumption — review before pitching
A10: KEY ASSUMPTIONS (the things that drive every other number)
A12: CABIN CLASS RETAIL PRICES
A13: Tier | B13: Monthly Retail | C13: Annualized | D13: GB Pool | E13: Carry-over % | F13: Notes
A14: Economy (pay-per-trip) | B14: 4.99 | C14: =B14*12 | D14: 1 | E14: 0 | F14: Avg per trip · 1GB/1-day · no carry
A15: Roster Bundle | B15: 39.99 | C15: =B15*12 | D15: 10 | E15: 0.5 | F15: 10GB pool · 50% carry
A16: Premium Economy | B16: 12.99 | C16: =B16*12 | D16: 15 | E16: 0.7 | F16: 15GB pool · 70% carry · 1 oops · RECOMMENDED
A17: Business | B17: 24.99 | C17: =B17*12 | D17: 8 | E17: 1 | F17: 20GB pool · 100% carry × 2 months max · 2 oops
A18: First | B18: 49.99 | C18: =B18*12 | D18: 12 | E18: 0.8 | F18: $299/yr · 12GB pool + 12GB lifetime emergency bank · 100% carry
A19: Cockpit Annual | B19: 24.92 | C19: 299 | D19: 30 | E19: 1 | F19: $299/yr · unlimited carry
A20: Refuel (add-on) | B20: 5.99 | C20: =B20*12 | D20: 1 | E20: 0 | F20: Avg top-up
A23: GEO COST BUCKETS (1GB / 1-day eSIM wholesale)
A24: Bucket | B24: Description | C24: Cost USD | D24: % Mix
A25: Tier-A (cheap) | B25: JP, UK, SG, MY, HK, KR, US | C25: 0.97 | D25: 0.6
A26: Tier-B (medium) | B26: CA, AU, NZ, VN, UAE | C26: 1.5 | D26: 0.25
A27: Tier-C (expensive) | B27: IN, BR, SA, ZA | C27: 5.8 | D27: 0.15
A29: BLENDED COST / GB | C29: =SUMPRODUCT(C25:C27,D25:D27)
A32: CABIN-CLASS MIX (% of paying users in each tier)
A33: Tier | B33: % Users
A34: Economy | B34: 0.3
A35: Roster Bundle | B35: 0.35
A36: Premium Economy | B36: 0.15
A37: Business | B37: 0.12
A38: First | B38: 0.05
A39: Cockpit | B39: 0.02
A40: Refuel attach | B40: 0.1
A43: OPERATING COST / USER / MONTH
A44: Line | B44: USD
A45: Cloud / API per user | B45: 0.15
A46: Payment processing (2.9% + $0.30) | B46: 0.5
A47: Customer support amortized | B47: 0.3
A48: SMS / OTP / verification | B48: 0.05
A49: Hosting + dev tools amortized | B49: 0.1
A50: TOTAL OPEX | B50: =SUM(B45:B49)

Sheet User Behavior
A1: User Behavior Profiles — % of pool consumed by user type
A2: For each tier, model 4 user types. % of pool consumed determines COGS in pay-per-order model.
A4: BEHAVIOR PROFILES (apply to all tiers)
A5: Profile | B5: % of Users | C5: % of Pool Consumed | D5: Refuel Attach Rate | E5: Notes
A6: Light user | B6: 0.4 | C6: 0.3 | D6: 0.05 | E6: Subscribes for peace-of-mind, barely uses pool
A7: Average user | B7: 0.35 | C7: 0.65 | D7: 0.15 | E7: Normal consumption, occasionally over
A8: Heavy user | B8: 0.2 | C8: 0.95 | D8: 0.5 | E8: Power user, often refuels
A9: Churner | B9: 0.05 | C9: 0.1 | D9: 0 | E9: Tries one month, cancels — pure breakage
A10: TOTAL | B10: =SUM(B6:B9)
A11: WEIGHTED AVG % POOL CONSUMED | C11: =SUMPRODUCT(B6:B9,C6:C9)
A12: WEIGHTED AVG REFUEL ATTACH | D12: =SUMPRODUCT(B6:B9,D6:D9)
A15: EXPECTED GB CONSUMED PER USER PER MONTH (by tier)
A16: Tier | B16: Pool GB | C16: % Consumed | D16: GB Consumed | E16: GB Unused (carries) | F16: GB Truly Unused (breakage)
A17: Economy | B17: ='README & Assumptions'!D14 | C17: =$C$11 | D17: =B17*C17 | E17: =(B17-D17)*'README & Assumptions'!E14 | F17: =(B17-D17)*(1-'README & Assumptions'!E14)
A18: Roster Bundle | B18: ='README & Assumptions'!D15 | C18: =$C$11 | D18: =B18*C18 | E18: =(B18-D18)*'README & Assumptions'!E15 | F18: =(B18-D18)*(1-'README & Assumptions'!E15)
A19: Premium Economy | B19: ='README & Assumptions'!D16 | C19: =$C$11 | D19: =B19*C19 | E19: =(B19-D19)*'README & Assumptions'!E16 | F19: =(B19-D19)*(1-'README & Assumptions'!E16)
A20: Business | B20: ='README & Assumptions'!D17 | C20: =$C$11 | D20: =B20*C20 | E20: =(B20-D20)*'README & Assumptions'!E17 | F20: =(B20-D20)*(1-'README & Assumptions'!E17)
A21: First | B21: ='README & Assumptions'!D18 | C21: =$C$11 | D21: =B21*C21 | E21: =(B21-D21)*'README & Assumptions'!E18 | F21: =(B21-D21)*(1-'README & Assumptions'!E18)
A22: Cockpit | B22: ='README & Assumptions'!D19 | C22: =$C$11 | D22: =B22*C22 | E22: =(B22-D22)*'README & Assumptions'!E19 | F22: =(B22-D22)*(1-'README & Assumptions'!E19)
A23: Refuel attach | B23: ='README & Assumptions'!D20 | C23: =$C$11 | D23: =B23*C23 | E23: =(B23-D23)*'README & Assumptions'!E20 | F23: =(B23-D23)*(1-'README & Assumptions'!E20)

Sheet Per-Tier Unit Economics
A1: Per-Tier Unit Economics (PAY-PER-ORDER model)
A2: COGS = actual GB consumed × wholesale cost. Unused GB that breaks is pure breakage revenue.
A4: Tier | B4: Monthly Revenue | C4: GB Consumed | D4: Wholesale $/GB | E4: eSIM COGS | F4: Refuel Revenue | G4: Refuel COGS | H4: Refund Cost | I4: Gross Profit | J4: Gross Margin % | K4: After Opex | L4: Net Margin %
A5: Economy | B5: ='README & Assumptions'!B13 | C5: ='User Behavior'!D17 | D5: ='README & Assumptions'!C29 | E5: =C5*D5 | F5: =5.99*'User Behavior'!D12 | G5: =D5*'User Behavior'!D12 | H5: =2.50*0.5*SUMPRODUCT('User Behavior'!B6:B9,'User Behavior'!C6:C9)/1 | I5: =B5+F5-E5-G5-H5 | J5: =IFERROR(I5/(B5+F5),0) | K5: =I5-'README & Assumptions'!B50 | L5: =IFERROR(K5/(B5+F5),0)
A6: Roster Bundle | B6: ='README & Assumptions'!B14 | C6: ='User Behavior'!D18 | D6: ='README & Assumptions'!C29 | E6: =C6*D6 | F6: =5.99*'User Behavior'!D12 | G6: =D6*'User Behavior'!D12 | H6: =2.50*0.5*SUMPRODUCT('User Behavior'!B6:B9,'User Behavior'!C6:C9)/1 | I6: =B6+F6-E6-G6-H6 | J6: =IFERROR(I6/(B6+F6),0) | K6: =I6-'README & Assumptions'!B50 | L6: =IFERROR(K6/(B6+F6),0)
A7: Premium Economy | B7: ='README & Assumptions'!B15 | C7: ='User Behavior'!D19 | D7: ='README & Assumptions'!C29 | E7: =C7*D7 | F7: =5.99*'User Behavior'!D12 | G7: =D7*'User Behavior'!D12 | H7: =2.50*0.5*SUMPRODUCT('User Behavior'!B6:B9,'User Behavior'!C6:C9)/1 | I7: =B7+F7-E7-G7-H7 | J7: =IFERROR(I7/(B7+F7),0) | K7: =I7-'README & Assumptions'!B50 | L7: =IFERROR(K7/(B7+F7),0)
A8: Business | B8: ='README & Assumptions'!B16 | C8: ='User Behavior'!D20 | D8: ='README & Assumptions'!C29 | E8: =C8*D8 | F8: =5.99*'User Behavior'!D12 | G8: =D8*'User Behavior'!D12 | H8: =2.50*0.5*SUMPRODUCT('User Behavior'!B6:B9,'User Behavior'!C6:C9)/1 | I8: =B8+F8-E8-G8-H8 | J8: =IFERROR(I8/(B8+F8),0) | K8: =I8-'README & Assumptions'!B50 | L8: =IFERROR(K8/(B8+F8),0)
A9: First | B9: ='README & Assumptions'!B17 | C9: ='User Behavior'!D21 | D9: ='README & Assumptions'!C29 | E9: =C9*D9 | F9: =5.99*'User Behavior'!D12 | G9: =D9*'User Behavior'!D12 | H9: =2.50*0.5*SUMPRODUCT('User Behavior'!B6:B9,'User Behavior'!C6:C9)/1 | I9: =B9+F9-E9-G9-H9 | J9: =IFERROR(I9/(B9+F9),0) | K9: =I9-'README & Assumptions'!B50 | L9: =IFERROR(K9/(B9+F9),0)
A10: Cockpit | B10: ='README & Assumptions'!B18 | C10: ='User Behavior'!D22 | D10: ='README & Assumptions'!C29 | E10: =C10*D10 | F10: =5.99*'User Behavior'!D12 | G10: =D10*'User Behavior'!D12 | H10: =2.50*0.5*SUMPRODUCT('User Behavior'!B6:B9,'User Behavior'!C6:C9)/1 | I10: =B10+F10-E10-G10-H10 | J10: =IFERROR(I10/(B10+F10),0) | K10: =I10-'README & Assumptions'!B50 | L10: =IFERROR(K10/(B10+F10),0)
A11: Refuel attach | B11: ='README & Assumptions'!B19 | C11: ='User Behavior'!D23 | D11: ='README & Assumptions'!C29 | E11: =C11*D11 | F11: =5.99*'User Behavior'!D12 | G11: =D11*'User Behavior'!D12 | H11: =2.50*0.5*SUMPRODUCT('User Behavior'!B6:B9,'User Behavior'!C6:C9)/1 | I11: =B11+F11-E11-G11-H11 | J11: =IFERROR(I11/(B11+F11),0) | K11: =I11-'README & Assumptions'!B50 | L11: =IFERROR(K11/(B11+F11),0)

Sheet Volume Scenarios
A1: Monthly P&L across 4 scale scenarios
A4: Scenario | B4: Active Users | C4: Monthly Revenue | D4: Monthly COGS | E4: Monthly Gross Profit | F4: Gross Margin % | G4: Monthly Opex | H4: Monthly Net Profit | I4: Net Margin % | J4: Annual Net
A5: Conservative | B5: 100 | C5: =B5*SUMPRODUCT('Per-Tier Unit Economics'!B5:B11+'Per-Tier Unit Economics'!F5:F11,'README & Assumptions'!B34:B40) | D5: =B5*SUMPRODUCT('Per-Tier Unit Economics'!E5:E11+'Per-Tier Unit Economics'!G5:G11+'Per-Tier Unit Economics'!H5:H11,'README & Assumptions'!B34:B40) | E5: =C5-D5 | F5: =IFERROR(E5/C5,0) | G5: =B5*'README & Assumptions'!B50 | H5: =E5-G5 | I5: =IFERROR(H5/C5,0) | J5: =H5*12
A6: Base | B6: 1000 | C6: =B6*SUMPRODUCT('Per-Tier Unit Economics'!B5:B11+'Per-Tier Unit Economics'!F5:F11,'README & Assumptions'!B34:B40) | D6: =B6*SUMPRODUCT('Per-Tier Unit Economics'!E5:E11+'Per-Tier Unit Economics'!G5:G11+'Per-Tier Unit Economics'!H5:H11,'README & Assumptions'!B34:B40) | E6: =C6-D6 | F6: =IFERROR(E6/C6,0) | G6: =B6*'README & Assumptions'!B50 | H6: =E6-G6 | I6: =IFERROR(H6/C6,0) | J6: =H6*12
A7: Aggressive | B7: 5000 | C7: =B7*SUMPRODUCT('Per-Tier Unit Economics'!B5:B11+'Per-Tier Unit Economics'!F5:F11,'README & Assumptions'!B34:B40) | D7: =B7*SUMPRODUCT('Per-Tier Unit Economics'!E5:E11+'Per-Tier Unit Economics'!G5:G11+'Per-Tier Unit Economics'!H5:H11,'README & Assumptions'!B34:B40) | E7: =C7-D7 | F7: =IFERROR(E7/C7,0) | G7: =B7*'README & Assumptions'!B50 | H7: =E7-G7 | I7: =IFERROR(H7/C7,0) | J7: =H7*12
A8: Hockey Stick | B8: 20000 | C8: =B8*SUMPRODUCT('Per-Tier Unit Economics'!B5:B11+'Per-Tier Unit Economics'!F5:F11,'README & Assumptions'!B34:B40) | D8: =B8*SUMPRODUCT('Per-Tier Unit Economics'!E5:E11+'Per-Tier Unit Economics'!G5:G11+'Per-Tier Unit Economics'!H5:H11,'README & Assumptions'!B34:B40) | E8: =C8-D8 | F8: =IFERROR(E8/C8,0) | G8: =B8*'README & Assumptions'!B50 | H8: =E8-G8 | I8: =IFERROR(H8/C8,0) | J8: =H8*12

Sheet Procurement Options
A1: Supply Procurement Options — same volume, 3 supply chains
A2: Compare current Samurai pay-per-order vs. bulk-prepay vs. eSIM Access direct at 1,000 users.
A4: OPTIONS
A5: Option | B5: Cost Modifier | C5: Breakage Cost | D5: Platform Fee/mo | E5: Description
A6: A. Samurai pay-per-order | B6: 1 | C6: 0 | D6: 0 | E6: Current model: COGS = consumed only, no upfront commitment
A7: B. Samurai bulk prepay -10% | B7: 0.9 | C7: 0.15 | D7: 0 | E7: 10% discount but pre-buy 100% of pool, 15% breakage on unused inventory
A8: C. eSIM Access direct -40% | B8: 0.6 | C8: 0 | D8: 5000 | E8: Bypass Samurai, save 40% but $5K/mo platform commitment
A10: COMPARISON @ 1,000 active users
A11: Option | B11: Monthly Revenue | C11: Effective COGS | D11: Platform Fee | E11: Net Profit | F11: Net Margin % | G11: Annual Net
A12: A. Samurai pay-per-order | B12: =1000*SUMPRODUCT('Per-Tier Unit Economics'!B5:B11+'Per-Tier Unit Economics'!F5:F11,'README & Assumptions'!B34:B40) | C12: =1000*SUMPRODUCT('Per-Tier Unit Economics'!E5:E11+'Per-Tier Unit Economics'!G5:G11+'Per-Tier Unit Economics'!H5:H11,'README & Assumptions'!B34:B40)*B6 | D12: =D6 | E12: =B12-C12-D12-(1000*'README & Assumptions'!B50) | F12: =IFERROR(E12/B12,0) | G12: =E12*12
A13: B. Samurai bulk prepay -10% | B13: =1000*SUMPRODUCT('Per-Tier Unit Economics'!B5:B11+'Per-Tier Unit Economics'!F5:F11,'README & Assumptions'!B34:B40) | C13: =1000*SUMPRODUCT('User Behavior'!B17:B23,'README & Assumptions'!B34:B40)*'README & Assumptions'!C29*B7 | D13: =D7 | E13: =B13-C13-D13-(1000*'README & Assumptions'!B50) | F13: =IFERROR(E13/B13,0) | G13: =E13*12
A14: C. eSIM Access direct -40% | B14: =1000*SUMPRODUCT('Per-Tier Unit Economics'!B5:B11+'Per-Tier Unit Economics'!F5:F11,'README & Assumptions'!B34:B40) | C14: =1000*SUMPRODUCT('Per-Tier Unit Economics'!E5:E11+'Per-Tier Unit Economics'!G5:G11+'Per-Tier Unit Economics'!H5:H11,'README & Assumptions'!B34:B40)*B8 | D14: =D8 | E14: =B14-C14-D14-(1000*'README & Assumptions'!B50) | F14: =IFERROR(E14/B14,0) | G14: =E14*12

Sheet 24-Month Rollout
A1: 24-Month Rollout — Base Scenario S-curve
A4: Month | B4: Active Users | C4: Revenue | D4: COGS | E4: Opex | F4: Net Profit | G4: Cumulative Profit
A5: M1 | B5: 50 | C5: =B5*SUMPRODUCT('Per-Tier Unit Economics'!B5:B11+'Per-Tier Unit Economics'!F5:F11,'README & Assumptions'!B34:B40) | D5: =B5*SUMPRODUCT('Per-Tier Unit Economics'!E5:E11+'Per-Tier Unit Economics'!G5:G11+'Per-Tier Unit Economics'!H5:H11,'README & Assumptions'!B34:B40) | E5: =B5*'README & Assumptions'!B50 | F5: =C5-D5-E5 | G5: =F5
A6: M2 | B6: 80 | C6: =B6*SUMPRODUCT('Per-Tier Unit Economics'!B5:B11+'Per-Tier Unit Economics'!F5:F11,'README & Assumptions'!B34:B40) | D6: =B6*SUMPRODUCT('Per-Tier Unit Economics'!E5:E11+'Per-Tier Unit Economics'!G5:G11+'Per-Tier Unit Economics'!H5:H11,'README & Assumptions'!B34:B40) | E6: =B6*'README & Assumptions'!B50 | F6: =C6-D6-E6 | G6: =G5+F6
A7: M3 | B7: 130 | C7: =B7*SUMPRODUCT('Per-Tier Unit Economics'!B5:B11+'Per-Tier Unit Economics'!F5:F11,'README & Assumptions'!B34:B40) | D7: =B7*SUMPRODUCT('Per-Tier Unit Economics'!E5:E11+'Per-Tier Unit Economics'!G5:G11+'Per-Tier Unit Economics'!H5:H11,'README & Assumptions'!B34:B40) | E7: =B7*'README & Assumptions'!B50 | F7: =C7-D7-E7 | G7: =G6+F7
A8: M4 | B8: 200 | C8: =B8*SUMPRODUCT('Per-Tier Unit Economics'!B5:B11+'Per-Tier Unit Economics'!F5:F11,'README & Assumptions'!B34:B40) | D8: =B8*SUMPRODUCT('Per-Tier Unit Economics'!E5:E11+'Per-Tier Unit Economics'!G5:G11+'Per-Tier Unit Economics'!H5:H11,'README & Assumptions'!B34:B40) | E8: =B8*'README & Assumptions'!B50 | F8: =C8-D8-E8 | G8: =G7+F8
A9: M5 | B9: 300 | C9: =B9*SUMPRODUCT('Per-Tier Unit Economics'!B5:B11+'Per-Tier Unit Economics'!F5:F11,'README & Assumptions'!B34:B40) | D9: =B9*SUMPRODUCT('Per-Tier Unit Economics'!E5:E11+'Per-Tier Unit Economics'!G5:G11+'Per-Tier Unit Economics'!H5:H11,'README & Assumptions'!B34:B40) | E9: =B9*'README & Assumptions'!B50 | F9: =C9-D9-E9 | G9: =G8+F9
A10: M6 | B10: 450 | C10: =B10*SUMPRODUCT('Per-Tier Unit Economics'!B5:B11+'Per-Tier Unit Economics'!F5:F11,'README & Assumptions'!B34:B40) | D10: =B10*SUMPRODUCT('Per-Tier Unit Economics'!E5:E11+'Per-Tier Unit Economics'!G5:G11+'Per-Tier Unit Economics'!H5:H11,'README & Assumptions'!B34:B40) | E10: =B10*'README & Assumptions'!B50 | F10: =C10-D10-E10 | G10: =G9+F10
A11: M7 | B11: 650 | C11: =B11*SUMPRODUCT('Per-Tier Unit Economics'!B5:B11+'Per-Tier Unit Economics'!F5:F11,'README & Assumptions'!B34:B40) | D11: =B11*SUMPRODUCT('Per-Tier Unit Economics'!E5:E11+'Per-Tier Unit Economics'!G5:G11+'Per-Tier Unit Economics'!H5:H11,'README & Assumptions'!B34:B40) | E11: =B11*'README & Assumptions'!B50 | F11: =C11-D11-E11 | G11: =G10+F11
A12: M8 | B12: 900 | C12: =B12*SUMPRODUCT('Per-Tier Unit Economics'!B5:B11+'Per-Tier Unit Economics'!F5:F11,'README & Assumptions'!B34:B40) | D12: =B12*SUMPRODUCT('Per-Tier Unit Economics'!E5:E11+'Per-Tier Unit Economics'!G5:G11+'Per-Tier Unit Economics'!H5:H11,'README & Assumptions'!B34:B40) | E12: =B12*'README & Assumptions'!B50 | F12: =C12-D12-E12 | G12: =G11+F12
A13: M9 | B13: 1200 | C13: =B13*SUMPRODUCT('Per-Tier Unit Economics'!B5:B11+'Per-Tier Unit Economics'!F5:F11,'README & Assumptions'!B34:B40) | D13: =B13*SUMPRODUCT('Per-Tier Unit Economics'!E5:E11+'Per-Tier Unit Economics'!G5:G11+'Per-Tier Unit Economics'!H5:H11,'README & Assumptions'!B34:B40) | E13: =B13*'README & Assumptions'!B50 | F13: =C13-D13-E13 | G13: =G12+F13
A14: M10 | B14: 1500 | C14: =B14*SUMPRODUCT('Per-Tier Unit Economics'!B5:B11+'Per-Tier Unit Economics'!F5:F11,'README & Assumptions'!B34:B40) | D14: =B14*SUMPRODUCT('Per-Tier Unit Economics'!E5:E11+'Per-Tier Unit Economics'!G5:G11+'Per-Tier Unit Economics'!H5:H11,'README & Assumptions'!B34:B40) | E14: =B14*'README & Assumptions'!B50 | F14: =C14-D14-E14 | G14: =G13+F14
A15: M11 | B15: 1800 | C15: =B15*SUMPRODUCT('Per-Tier Unit Economics'!B5:B11+'Per-Tier Unit Economics'!F5:F11,'README & Assumptions'!B34:B40) | D15: =B15*SUMPRODUCT('Per-Tier Unit Economics'!E5:E11+'Per-Tier Unit Economics'!G5:G11+'Per-Tier Unit Economics'!H5:H11,'README & Assumptions'!B34:B40) | E15: =B15*'README & Assumptions'!B50 | F15: =C15-D15-E15 | G15: =G14+F15
A16: M12 | B16: 2100 | C16: =B16*SUMPRODUCT('Per-Tier Unit Economics'!B5:B11+'Per-Tier Unit Economics'!F5:F11,'README & Assumptions'!B34:B40) | D16: =B16*SUMPRODUCT('Per-Tier Unit Economics'!E5:E11+'Per-Tier Unit Economics'!G5:G11+'Per-Tier Unit Economics'!H5:H11,'README & Assumptions'!B34:B40) | E16: =B16*'README & Assumptions'!B50 | F16: =C16-D16-E16 | G16: =G15+F16
A17: M13 | B17: 2400 | C17: =B17*SUMPRODUCT('Per-Tier Unit Economics'!B5:B11+'Per-Tier Unit Economics'!F5:F11,'README & Assumptions'!B34:B40) | D17: =B17*SUMPRODUCT('Per-Tier Unit Economics'!E5:E11+'Per-Tier Unit Economics'!G5:G11+'Per-Tier Unit Economics'!H5:H11,'README & Assumptions'!B34:B40) | E17: =B17*'README & Assumptions'!B50 | F17: =C17-D17-E17 | G17: =G16+F17
A18: M14 | B18: 2700 | C18: =B18*SUMPRODUCT('Per-Tier Unit Economics'!B5:B11+'Per-Tier Unit Economics'!F5:F11,'README & Assumptions'!B34:B40) | D18: =B18*SUMPRODUCT('Per-Tier Unit Economics'!E5:E11+'Per-Tier Unit Economics'!G5:G11+'Per-Tier Unit Economics'!H5:H11,'README & Assumptions'!B34:B40) | E18: =B18*'README & Assumptions'!B50 | F18: =C18-D18-E18 | G18: =G17+F18
A19: M15 | B19: 3000 | C19: =B19*SUMPRODUCT('Per-Tier Unit Economics'!B5:B11+'Per-Tier Unit Economics'!F5:F11,'README & Assumptions'!B34:B40) | D19: =B19*SUMPRODUCT('Per-Tier Unit Economics'!E5:E11+'Per-Tier Unit Economics'!G5:G11+'Per-Tier Unit Economics'!H5:H11,'README & Assumptions'!B34:B40) | E19: =B19*'README & Assumptions'!B50 | F19: =C19-D19-E19 | G19: =G18+F19
A20: M16 | B20: 3300 | C20: =B20*SUMPRODUCT('Per-Tier Unit Economics'!B5:B11+'Per-Tier Unit Economics'!F5:F11,'README & Assumptions'!B34:B40) | D20: =B20*SUMPRODUCT('Per-Tier Unit Economics'!E5:E11+'Per-Tier Unit Economics'!G5:G11+'Per-Tier Unit Economics'!H5:H11,'README & Assumptions'!B34:B40) | E20: =B20*'README & Assumptions'!B50 | F20: =C20-D20-E20 | G20: =G19+F20
A21: M17 | B21: 3600 | C21: =B21*SUMPRODUCT('Per-Tier Unit Economics'!B5:B11+'Per-Tier Unit Economics'!F5:F11,'README & Assumptions'!B34:B40) | D21: =B21*SUMPRODUCT('Per-Tier Unit Economics'!E5:E11+'Per-Tier Unit Economics'!G5:G11+'Per-Tier Unit Economics'!H5:H11,'README & Assumptions'!B34:B40) | E21: =B21*'README & Assumptions'!B50 | F21: =C21-D21-E21 | G21: =G20+F21
A22: M18 | B22: 3900 | C22: =B22*SUMPRODUCT('Per-Tier Unit Economics'!B5:B11+'Per-Tier Unit Economics'!F5:F11,'README & Assumptions'!B34:B40) | D22: =B22*SUMPRODUCT('Per-Tier Unit Economics'!E5:E11+'Per-Tier Unit Economics'!G5:G11+'Per-Tier Unit Economics'!H5:H11,'README & Assumptions'!B34:B40) | E22: =B22*'README & Assumptions'!B50 | F22: =C22-D22-E22 | G22: =G21+F22
A23: M19 | B23: 4200 | C23: =B23*SUMPRODUCT('Per-Tier Unit Economics'!B5:B11+'Per-Tier Unit Economics'!F5:F11,'README & Assumptions'!B34:B40) | D23: =B23*SUMPRODUCT('Per-Tier Unit Economics'!E5:E11+'Per-Tier Unit Economics'!G5:G11+'Per-Tier Unit Economics'!H5:H11,'README & Assumptions'!B34:B40) | E23: =B23*'README & Assumptions'!B50 | F23: =C23-D23-E23 | G23: =G22+F23
A24: M20 | B24: 4500 | C24: =B24*SUMPRODUCT('Per-Tier Unit Economics'!B5:B11+'Per-Tier Unit Economics'!F5:F11,'README & Assumptions'!B34:B40) | D24: =B24*SUMPRODUCT('Per-Tier Unit Economics'!E5:E11+'Per-Tier Unit Economics'!G5:G11+'Per-Tier Unit Economics'!H5:H11,'README & Assumptions'!B34:B40) | E24: =B24*'README & Assumptions'!B50 | F24: =C24-D24-E24 | G24: =G23+F24
A25: M21 | B25: 4700 | C25: =B25*SUMPRODUCT('Per-Tier Unit Economics'!B5:B11+'Per-Tier Unit Economics'!F5:F11,'README & Assumptions'!B34:B40) | D25: =B25*SUMPRODUCT('Per-Tier Unit Economics'!E5:E11+'Per-Tier Unit Economics'!G5:G11+'Per-Tier Unit Economics'!H5:H11,'README & Assumptions'!B34:B40) | E25: =B25*'README & Assumptions'!B50 | F25: =C25-D25-E25 | G25: =G24+F25
A26: M22 | B26: 4850 | C26: =B26*SUMPRODUCT('Per-Tier Unit Economics'!B5:B11+'Per-Tier Unit Economics'!F5:F11,'README & Assumptions'!B34:B40) | D26: =B26*SUMPRODUCT('Per-Tier Unit Economics'!E5:E11+'Per-Tier Unit Economics'!G5:G11+'Per-Tier Unit Economics'!H5:H11,'README & Assumptions'!B34:B40) | E26: =B26*'README & Assumptions'!B50 | F26: =C26-D26-E26 | G26: =G25+F26
A27: M23 | B27: 4950 | C27: =B27*SUMPRODUCT('Per-Tier Unit Economics'!B5:B11+'Per-Tier Unit Economics'!F5:F11,'README & Assumptions'!B34:B40) | D27: =B27*SUMPRODUCT('Per-Tier Unit Economics'!E5:E11+'Per-Tier Unit Economics'!G5:G11+'Per-Tier Unit Economics'!H5:H11,'README & Assumptions'!B34:B40) | E27: =B27*'README & Assumptions'!B50 | F27: =C27-D27-E27 | G27: =G26+F27
A28: M24 | B28: 5000 | C28: =B28*SUMPRODUCT('Per-Tier Unit Economics'!B5:B11+'Per-Tier Unit Economics'!F5:F11,'README & Assumptions'!B34:B40) | D28: =B28*SUMPRODUCT('Per-Tier Unit Economics'!E5:E11+'Per-Tier Unit Economics'!G5:G11+'Per-Tier Unit Economics'!H5:H11,'README & Assumptions'!B34:B40) | E28: =B28*'README & Assumptions'!B50 | F28: =C28-D28-E28 | G28: =G27+F28
A29: 24-MO TOTAL | C29: =SUM(C5:C28) | D29: =SUM(D5:D28) | E29: =SUM(E5:E28) | F29: =SUM(F5:F28) | G29: =G28

Sheet Behavior Sensitivity
A1: Behavior Sensitivity — net profit vs user behavior mix @ 1,000 users
A2: How much of the 'pool unused = breakage revenue' effect changes with user behavior.
A4: Mix Profile | B4: % Light | C4: % Average | D4: % Heavy | E4: % Churner | F4: Avg % Consumed | G4: Monthly Net | H4: Net Margin %
A5: Healthy SaaS (lots of light users) | B5: 0.55 | C5: 0.3 | D5: 0.1 | E5: 0.05 | F5: =B5*0.30+C5*0.65+D5*0.95+E5*0.10 | G5: =(1000*SUMPRODUCT('Per-Tier Unit Economics'!B5:B11+'Per-Tier Unit Economics'!F5:F11,'README & Assumptions'!B34:B40))-(1000*SUMPRODUCT('User Behavior'!B17:B23,'README & Assumptions'!B34:B40)*'README & Assumptions'!C29*F5)-(1000*'README & Assumptions'!B50) | H5: =IFERROR(G5/(1000*SUMPRODUCT('Per-Tier Unit Economics'!B5:B11+'Per-Tier Unit Economics'!F5:F11,'README & Assumptions'!B34:B40)),0)
A6: Base (current model) | B6: 0.4 | C6: 0.35 | D6: 0.2 | E6: 0.05 | F6: =B6*0.30+C6*0.65+D6*0.95+E6*0.10 | G6: =(1000*SUMPRODUCT('Per-Tier Unit Economics'!B5:B11+'Per-Tier Unit Economics'!F5:F11,'README & Assumptions'!B34:B40))-(1000*SUMPRODUCT('User Behavior'!B17:B23,'README & Assumptions'!B34:B40)*'README & Assumptions'!C29*F6)-(1000*'README & Assumptions'!B50) | H6: =IFERROR(G6/(1000*SUMPRODUCT('Per-Tier Unit Economics'!B5:B11+'Per-Tier Unit Economics'!F5:F11,'README & Assumptions'!B34:B40)),0)
A7: Heavy crew (power users dominate) | B7: 0.2 | C7: 0.3 | D7: 0.45 | E7: 0.05 | F7: =B7*0.30+C7*0.65+D7*0.95+E7*0.10 | G7: =(1000*SUMPRODUCT('Per-Tier Unit Economics'!B5:B11+'Per-Tier Unit Economics'!F5:F11,'README & Assumptions'!B34:B40))-(1000*SUMPRODUCT('User Behavior'!B17:B23,'README & Assumptions'!B34:B40)*'README & Assumptions'!C29*F7)-(1000*'README & Assumptions'!B50) | H7: =IFERROR(G7/(1000*SUMPRODUCT('Per-Tier Unit Economics'!B5:B11+'Per-Tier Unit Economics'!F5:F11,'README & Assumptions'!B34:B40)),0)
A8: High churn (bad acquisition) | B8: 0.3 | C8: 0.25 | D8: 0.15 | E8: 0.3 | F8: =B8*0.30+C8*0.65+D8*0.95+E8*0.10 | G8: =(1000*SUMPRODUCT('Per-Tier Unit Economics'!B5:B11+'Per-Tier Unit Economics'!F5:F11,'README & Assumptions'!B34:B40))-(1000*SUMPRODUCT('User Behavior'!B17:B23,'README & Assumptions'!B34:B40)*'README & Assumptions'!C29*F8)-(1000*'README & Assumptions'!B50) | H8: =IFERROR(G8/(1000*SUMPRODUCT('Per-Tier Unit Economics'!B5:B11+'Per-Tier Unit Economics'!F5:F11,'README & Assumptions'!B34:B40)),0)

Sheet LTV-CAC + Churn
A1: LTV / CAC + Per-Tier Churn
A2: How much can we spend to acquire each tier? LTV:CAC > 3 is investable, > 5 is excellent.
A4: PER-TIER MONTHLY CHURN
A5: Tier | B5: Monthly Churn % | C5: Avg Lifetime (mo) | D5: Notes
A6: Economy | B6: 0.3 | C6: =IFERROR(1/B6,0) | D6: 1-month casuals, trial users
A7: Roster Bundle | B7: 0.08 | C7: =IFERROR(1/B7,0) | D7: Sticky once roster sync set up
A8: Premium Economy | B8: 0.12 | C8: =IFERROR(1/B8,0) | D8: Light commitment
A9: Business | B9: 0.06 | C9: =IFERROR(1/B9,0) | D9: Pool habit forms, high retention
A10: First | B10: 0.04 | C10: =IFERROR(1/B10,0) | D10: Power users, perks lock in
A11: Cockpit | B11: 0.03 | C11: =IFERROR(1/B11,0) | D11: Annual prepay = automatic 12-mo retention
A12: Refuel (add-on) | B12: 0.15 | C12: =IFERROR(1/B12,0) | D12: Per-purchase, no subscription
A15: CUSTOMER ACQUISITION COST (per-channel blended avg)
A16: Channel | B16: % of Acquisition | C16: $ CAC | D16: Notes
A17: Organic / word-of-mouth | B17: 0.5 | C17: 0 | D17: Crew network referrals — free
A18: Referral bonus ($5 credit) | B18: 0.25 | C18: 5 | D18: Existing user refers
A19: Paid social (IG/TikTok) | B19: 0.15 | C19: 12 | D19: Cold acquisition
A20: Influencer / crew creator | B20: 0.1 | C20: 8 | D20: Paid sponsorship to @crew_illust et al
A22: BLENDED CAC | C22: =SUMPRODUCT(B17:B20,C17:C20)
A25: LTV / CAC PER TIER (Gross Profit × Lifetime ÷ CAC)
A26: Tier | B26: Gross Profit/mo | C26: Lifetime (mo) | D26: LTV | E26: CAC | F26: LTV:CAC | G26: Payback (mo) | H26: Verdict
A27: Economy | B27: ='Per-Tier Unit Economics'!I5 | C27: =C6 | D27: =B27*C27 | E27: =$C$22 | F27: =IFERROR(D27/E27,0) | G27: =IFERROR(E27/B27,0) | H27: =IF(F27>=5,"Excellent",IF(F27>=3,"Investable",IF(F27>=1,"Marginal","Loss")))
A28: Roster Bundle | B28: ='Per-Tier Unit Economics'!I6 | C28: =C7 | D28: =B28*C28 | E28: =$C$22 | F28: =IFERROR(D28/E28,0) | G28: =IFERROR(E28/B28,0) | H28: =IF(F28>=5,"Excellent",IF(F28>=3,"Investable",IF(F28>=1,"Marginal","Loss")))
A29: Premium Economy | B29: ='Per-Tier Unit Economics'!I7 | C29: =C8 | D29: =B29*C29 | E29: =$C$22 | F29: =IFERROR(D29/E29,0) | G29: =IFERROR(E29/B29,0) | H29: =IF(F29>=5,"Excellent",IF(F29>=3,"Investable",IF(F29>=1,"Marginal","Loss")))
A30: Business | B30: ='Per-Tier Unit Economics'!I8 | C30: =C9 | D30: =B30*C30 | E30: =$C$22 | F30: =IFERROR(D30/E30,0) | G30: =IFERROR(E30/B30,0) | H30: =IF(F30>=5,"Excellent",IF(F30>=3,"Investable",IF(F30>=1,"Marginal","Loss")))
A31: First | B31: ='Per-Tier Unit Economics'!I9 | C31: =C10 | D31: =B31*C31 | E31: =$C$22 | F31: =IFERROR(D31/E31,0) | G31: =IFERROR(E31/B31,0) | H31: =IF(F31>=5,"Excellent",IF(F31>=3,"Investable",IF(F31>=1,"Marginal","Loss")))
A32: Cockpit | B32: ='Per-Tier Unit Economics'!I10 | C32: =C11 | D32: =B32*C32 | E32: =$C$22 | F32: =IFERROR(D32/E32,0) | G32: =IFERROR(E32/B32,0) | H32: =IF(F32>=5,"Excellent",IF(F32>=3,"Investable",IF(F32>=1,"Marginal","Loss")))
A33: Refuel | B33: ='Per-Tier Unit Economics'!I11 | C33: =C12 | D33: =B33*C33 | E33: =$C$22 | F33: =IFERROR(D33/E33,0) | G33: =IFERROR(E33/B33,0) | H33: =IF(F33>=5,"Excellent",IF(F33>=3,"Investable",IF(F33>=1,"Marginal","Loss")))

Sheet Per-Tier Geo Mix
A1: Per-Tier Geo Mix — different tiers fly different routes
A2: Roster Bundle users fly mostly crew layover countries (Tier-A). Economy users vacation in Tier-C (Bali/Maldives).
A4: Tier | B4: % Tier-A (cheap) | C4: % Tier-B (medium) | D4: % Tier-C (expensive) | E4: Effective Cost/GB | F4: Margin vs Default
A5: Economy | B5: 0.3 | C5: 0.3 | D5: 0.4 | E5: =B5*'README & Assumptions'!C25+C5*'README & Assumptions'!C26+D5*'README & Assumptions'!C27 | F5: ='README & Assumptions'!C29-E5
A6: Roster Bundle | B6: 0.7 | C6: 0.25 | D6: 0.05 | E6: =B6*'README & Assumptions'!C25+C6*'README & Assumptions'!C26+D6*'README & Assumptions'!C27 | F6: ='README & Assumptions'!C29-E6
A7: Premium Economy | B7: 0.55 | C7: 0.3 | D7: 0.15 | E7: =B7*'README & Assumptions'!C25+C7*'README & Assumptions'!C26+D7*'README & Assumptions'!C27 | F7: ='README & Assumptions'!C29-E7
A8: Business | B8: 0.6 | C8: 0.25 | D8: 0.15 | E8: =B8*'README & Assumptions'!C25+C8*'README & Assumptions'!C26+D8*'README & Assumptions'!C27 | F8: ='README & Assumptions'!C29-E8
A9: First | B9: 0.5 | C9: 0.3 | D9: 0.2 | E9: =B9*'README & Assumptions'!C25+C9*'README & Assumptions'!C26+D9*'README & Assumptions'!C27 | F9: ='README & Assumptions'!C29-E9
A10: Cockpit | B10: 0.65 | C10: 0.25 | D10: 0.1 | E10: =B10*'README & Assumptions'!C25+C10*'README & Assumptions'!C26+D10*'README & Assumptions'!C27 | F10: ='README & Assumptions'!C29-E10
A11: Refuel | B11: 0.6 | C11: 0.25 | D11: 0.15 | E11: =B11*'README & Assumptions'!C25+C11*'README & Assumptions'!C26+D11*'README & Assumptions'!C27 | F11: ='README & Assumptions'!C29-E11
A13: REVISED PER-TIER GROSS MARGIN (with tier-specific geo mix)
A14: Tier | B14: Monthly Revenue | C14: GB Consumed | D14: Effective $/GB | E14: Adjusted COGS | F14: Gross Profit | G14: Margin % | H14: vs Default
A15: Economy | B15: ='Per-Tier Unit Economics'!B5 | C15: ='Per-Tier Unit Economics'!C5 | D15: =E5 | E15: =C15*D15 | F15: =B15-E15 | G15: =IFERROR(F15/B15,0) | H15: =F15-'Per-Tier Unit Economics'!I5
A16: Roster Bundle | B16: ='Per-Tier Unit Economics'!B6 | C16: ='Per-Tier Unit Economics'!C6 | D16: =E6 | E16: =C16*D16 | F16: =B16-E16 | G16: =IFERROR(F16/B16,0) | H16: =F16-'Per-Tier Unit Economics'!I6
A17: Premium Economy | B17: ='Per-Tier Unit Economics'!B7 | C17: ='Per-Tier Unit Economics'!C7 | D17: =E7 | E17: =C17*D17 | F17: =B17-E17 | G17: =IFERROR(F17/B17,0) | H17: =F17-'Per-Tier Unit Economics'!I7
A18: Business | B18: ='Per-Tier Unit Economics'!B8 | C18: ='Per-Tier Unit Economics'!C8 | D18: =E8 | E18: =C18*D18 | F18: =B18-E18 | G18: =IFERROR(F18/B18,0) | H18: =F18-'Per-Tier Unit Economics'!I8
A19: First | B19: ='Per-Tier Unit Economics'!B9 | C19: ='Per-Tier Unit Economics'!C9 | D19: =E9 | E19: =C19*D19 | F19: =B19-E19 | G19: =IFERROR(F19/B19,0) | H19: =F19-'Per-Tier Unit Economics'!I9
A20: Cockpit | B20: ='Per-Tier Unit Economics'!B10 | C20: ='Per-Tier Unit Economics'!C10 | D20: =E10 | E20: =C20*D20 | F20: =B20-E20 | G20: =IFERROR(F20/B20,0) | H20: =F20-'Per-Tier Unit Economics'!I10
A21: Refuel | B21: ='Per-Tier Unit Economics'!B11 | C21: ='Per-Tier Unit Economics'!C11 | D21: =E11 | E21: =C21*D21 | F21: =B21-E21 | G21: =IFERROR(F21/B21,0) | H21: =F21-'Per-Tier Unit Economics'!I11

Sheet Carryover Liability
A1: Carryover Liability — GB you owe users
A2: Premium/Business/First/Cockpit carry unused GB. At any month you have $ liability if everyone redeems together.
A4: PER-TIER CARRYOVER (per user per month)
A5: Tier | B5: GB Pool | C5: % Consumed | D5: GB Unused | E5: Carry % | F5: GB Carried/mo | G5: $ Liability per user
A6: Economy | B6: ='README & Assumptions'!D14 | C6: ='User Behavior'!C11 | D6: =B6*(1-C6) | E6: ='README & Assumptions'!E14 | F6: =D6*E6 | G6: =F6*'README & Assumptions'!C29
A7: Roster Bundle | B7: ='README & Assumptions'!D15 | C7: ='User Behavior'!C11 | D7: =B7*(1-C7) | E7: ='README & Assumptions'!E15 | F7: =D7*E7 | G7: =F7*'README & Assumptions'!C29
A8: Premium Economy | B8: ='README & Assumptions'!D16 | C8: ='User Behavior'!C11 | D8: =B8*(1-C8) | E8: ='README & Assumptions'!E16 | F8: =D8*E8 | G8: =F8*'README & Assumptions'!C29
A9: Business | B9: ='README & Assumptions'!D17 | C9: ='User Behavior'!C11 | D9: =B9*(1-C9) | E9: ='README & Assumptions'!E17 | F9: =D9*E9 | G9: =F9*'README & Assumptions'!C29
A10: First | B10: ='README & Assumptions'!D18 | C10: ='User Behavior'!C11 | D10: =B10*(1-C10) | E10: ='README & Assumptions'!E18 | F10: =D10*E10 | G10: =F10*'README & Assumptions'!C29
A11: Cockpit | B11: ='README & Assumptions'!D19 | C11: ='User Behavior'!C11 | D11: =B11*(1-C11) | E11: ='README & Assumptions'!E19 | F11: =D11*E11 | G11: =F11*'README & Assumptions'!C29
A12: Refuel | B12: ='README & Assumptions'!D20 | C12: ='User Behavior'!C11 | D12: =B12*(1-C12) | E12: ='README & Assumptions'!E20 | F12: =D12*E12 | G12: =F12*'README & Assumptions'!C29
A15: CUMULATIVE LIABILITY OVER 12 MONTHS (at base 1,000 users, default mix)
A16: Assumes 20%/mo redemption rate. Net accrual = carried - redeemed each month.
A17: Month | B17: New Carryover | C17: Redeemed | D17: Net Balance | E17: $ Value @ blended cost
A18: Redemption rate | B18: 0.2
A19: M1 | B19: =1000*SUMPRODUCT(F6:F12,'README & Assumptions'!B34:B40) | C19: =0 | D19: =B19-C19 | E19: =D19*'README & Assumptions'!C29
A20: M2 | B20: =1000*SUMPRODUCT(F6:F12,'README & Assumptions'!B34:B40) | C20: =D19*$B$18 | D20: =D19+B20-C20 | E20: =D20*'README & Assumptions'!C29
A21: M3 | B21: =1000*SUMPRODUCT(F6:F12,'README & Assumptions'!B34:B40) | C21: =D20*$B$18 | D21: =D20+B21-C21 | E21: =D21*'README & Assumptions'!C29
A22: M4 | B22: =1000*SUMPRODUCT(F6:F12,'README & Assumptions'!B34:B40) | C22: =D21*$B$18 | D22: =D21+B22-C22 | E22: =D22*'README & Assumptions'!C29
A23: M5 | B23: =1000*SUMPRODUCT(F6:F12,'README & Assumptions'!B34:B40) | C23: =D22*$B$18 | D23: =D22+B23-C23 | E23: =D23*'README & Assumptions'!C29
A24: M6 | B24: =1000*SUMPRODUCT(F6:F12,'README & Assumptions'!B34:B40) | C24: =D23*$B$18 | D24: =D23+B24-C24 | E24: =D24*'README & Assumptions'!C29
A25: M7 | B25: =1000*SUMPRODUCT(F6:F12,'README & Assumptions'!B34:B40) | C25: =D24*$B$18 | D25: =D24+B25-C25 | E25: =D25*'README & Assumptions'!C29
A26: M8 | B26: =1000*SUMPRODUCT(F6:F12,'README & Assumptions'!B34:B40) | C26: =D25*$B$18 | D26: =D25+B26-C26 | E26: =D26*'README & Assumptions'!C29
A27: M9 | B27: =1000*SUMPRODUCT(F6:F12,'README & Assumptions'!B34:B40) | C27: =D26*$B$18 | D27: =D26+B27-C27 | E27: =D27*'README & Assumptions'!C29
A28: M10 | B28: =1000*SUMPRODUCT(F6:F12,'README & Assumptions'!B34:B40) | C28: =D27*$B$18 | D28: =D27+B28-C28 | E28: =D28*'README & Assumptions'!C29
A29: M11 | B29: =1000*SUMPRODUCT(F6:F12,'README & Assumptions'!B34:B40) | C29: =D28*$B$18 | D29: =D28+B29-C29 | E29: =D29*'README & Assumptions'!C29
A30: M12 | B30: =1000*SUMPRODUCT(F6:F12,'README & Assumptions'!B34:B40) | C30: =D29*$B$18 | D30: =D29+B30-C30 | E30: =D30*'README & Assumptions'!C29

Sheet Strategic Scenarios
A1: Strategic Scenarios — wholesale triggers + multi-airline + competitive floor
A2: Year 2-3 planning: when does scale unlock direct wholesale, what does multi-airline look like, where is our pricing floor.
A4: WHOLESALE TIER TRIGGERS — what volume unlocks better rates
A5: Volume (activations/mo) | B5: Samurai Markup (assumed) | C5: Effective Cost vs Default | D5: Direct eSIM Access | E5: Better Path
A6: 1000 | B6: 0.7 | C6: =(1+B6)/(1+0.70) | D6: $0.55 (60% lower) | E6: Stay with Samurai (no leverage yet)
A7: 5000 | B7: 0.55 | C7: =(1+B7)/(1+0.70) | D7: $0.55 (60% lower) | E7: Negotiate to 55%
A8: 10000 | B8: 0.4 | C8: =(1+B8)/(1+0.70) | D8: $0.55 (60% lower) | E8: Hit publicly-claimed 40%
A9: 25000 | B9: 0.3 | C9: =(1+B9)/(1+0.70) | D9: $0.55 (60% lower) | E9: Direct eSIM Access becomes equally attractive
A10: 50000 | B10: 0.2 | C10: =(1+B10)/(1+0.70) | D10: $0.55 (60% lower) | E10: Direct eSIM Access strictly cheaper
A11: 100000 | B11: 0.15 | C11: =(1+B11)/(1+0.70) | D11: $0.55 (60% lower) | E11: Direct contracts with MNOs available
A14: MULTI-AIRLINE EXPANSION
A15: Year | B15: Airlines | C15: Volume Multiplier | D15: Crew Base | E15: Active Users Estimate | F15: Annual Revenue Estimate
A16: Year 1 | B16: Emirates (DXB) | C16: 1 | D16: 24000 | E16: 1000 | F16: =E16*SUMPRODUCT('Per-Tier Unit Economics'!B5:B11+'Per-Tier Unit Economics'!F5:F11,'README & Assumptions'!B34:B40)*12
A17: Year 2 | B17: + Etihad (AUH), JAL (NRT), ANA (HND) | C17: 3 | D17: 80000 | E17: 6000 | F17: =E17*SUMPRODUCT('Per-Tier Unit Economics'!B5:B11+'Per-Tier Unit Economics'!F5:F11,'README & Assumptions'!B34:B40)*12
A18: Year 3 | B18: + Singapore, Cathay (HKG), Qatar | C18: 5 | D18: 140000 | E18: 18000 | F18: =E18*SUMPRODUCT('Per-Tier Unit Economics'!B5:B11+'Per-Tier Unit Economics'!F5:F11,'README & Assumptions'!B34:B40)*12
A21: CREW SIM COMPETITIVE FLOOR — minimum price before tier goes negative
A22: Crew SIM publishes rates for 41 countries. If they undercut, our floor = COGS + opex (zero margin)
A23: Tier | B23: Current Retail | C23: eSIM COGS | D23: Opex | E23: Min Viable Price | F23: Crew SIM Reference | G23: Margin Cushion
A24: Economy | B24: ='Per-Tier Unit Economics'!B5 | C24: ='Per-Tier Unit Economics'!E5 | D24: ='README & Assumptions'!B50 | E24: =C24+D24 | F24: 4.99 | G24: =F24-E24
A25: Roster Bundle | B25: ='Per-Tier Unit Economics'!B6 | C25: ='Per-Tier Unit Economics'!E6 | D25: ='README & Assumptions'!B50 | E25: =C25+D25 | F25: 35 | G25: =F25-E25
A26: Premium Economy | B26: ='Per-Tier Unit Economics'!B7 | C26: ='Per-Tier Unit Economics'!E7 | D26: ='README & Assumptions'!B50 | E26: =C26+D26 | F26: 12.99 | G26: =F26-E26
A27: Business | B27: ='Per-Tier Unit Economics'!B8 | C27: ='Per-Tier Unit Economics'!E8 | D27: ='README & Assumptions'!B50 | E27: =C27+D27 | F27: 21.99 | G27: =F27-E27
A28: First | B28: ='Per-Tier Unit Economics'!B9 | C28: ='Per-Tier Unit Economics'!E9 | D28: ='README & Assumptions'!B50 | E28: =C28+D28 | F28: 39.99 | G28: =F28-E28
A29: Cockpit | B29: ='Per-Tier Unit Economics'!B10 | C29: ='Per-Tier Unit Economics'!E10 | D29: ='README & Assumptions'!B50 | E29: =C29+D29 | F29: 24.99 | G29: =F29-E29
A30: Refuel | B30: ='Per-Tier Unit Economics'!B11 | C30: ='Per-Tier Unit Economics'!E11 | D30: ='README & Assumptions'!B50 | E30: =C30+D30 | F30: 5.99 | G30: =F30-E30

Sheet Cash + Sensitivity
A1: Cash vs Accrual + Refuel Sensitivity + Failed-eSIM Cost
A3: REFUEL ATTACH RATE SENSITIVITY (@ 1,000 users)
A4: Refuel Attach % | B4: Monthly Refuel Revenue | C4: Monthly Refuel COGS | D4: Net Refuel Profit | E4: Net Margin Impact
A5: 0.05 | B5: =1000*5.99*A5 | C5: =1000*'README & Assumptions'!C29*A5 | D5: =B5-C5 | E5: =D5-($D$7)
A6: 0.1 | B6: =1000*5.99*A6 | C6: =1000*'README & Assumptions'!C29*A6 | D6: =B6-C6 | E6: =D6-($D$7)
A7: 0.15 | B7: =1000*5.99*A7 | C7: =1000*'README & Assumptions'!C29*A7 | D7: =B7-C7 | E7: =D7-($D$7)
A8: 0.2 | B8: =1000*5.99*A8 | C8: =1000*'README & Assumptions'!C29*A8 | D8: =B8-C8 | E8: =D8-($D$7)
A9: 0.25 | B9: =1000*5.99*A9 | C9: =1000*'README & Assumptions'!C29*A9 | D9: =B9-C9 | E9: =D9-($D$7)
A10: 0.3 | B10: =1000*5.99*A10 | C10: =1000*'README & Assumptions'!C29*A10 | D10: =B10-C10 | E10: =D10-($D$7)
A13: FAILED-eSIM COST
A14: For every failed activation: refund + 2GB goodwill + reissue cost
A15: Failure Rate | B15: Cost per Failed Activation | C15: Failed/mo @ 1K users | D15: Monthly Cost | E15: Annual Cost
A16: 0.01 | B16: 4 | C16: =1000*A16*3 | D16: =C16*B16 | E16: =D16*12
A17: 0.02 | B17: 4 | C17: =1000*A17*3 | D17: =C17*B17 | E17: =D17*12
A18: 0.03 | B18: 4 | C18: =1000*A18*3 | D18: =C18*B18 | E18: =D18*12
A19: 0.05 | B19: 4 | C19: =1000*A19*3 | D19: =C19*B19 | E19: =D19*12
A20: 0.08 | B20: 4 | C20: =1000*A20*3 | D20: =C20*B20 | E20: =D20*12
A23: COCKPIT ANNUAL CASH ADVANTAGE
A24: $299 collected upfront vs $24.92/mo over 12 months. The cashflow boost matters for runway.
A25: Cockpit Users | B25: Monthly Sub Recognized | C25: Upfront Cash | D25: Cash Boost vs Monthly
A26: 10 | B26: =A26*24.92 | C26: =A26*299 | D26: =C26-(B26*12)
A27: 50 | B27: =A27*24.92 | C27: =A27*299 | D27: =C27-(B27*12)
A28: 100 | B28: =A28*24.92 | C28: =A28*299 | D28: =C28-(B28*12)
A29: 200 | B29: =A29*24.92 | C29: =A29*299 | D29: =C29-(B29*12)
A30: 500 | B30: =A30*24.92 | C30: =A30*299 | D30: =C30-(B30*12)
A31: 1000 | B31: =A31*24.92 | C31: =A31*299 | D31: =C31-(B31*12)
